pdic/__init__.py
pdic/__version__.py
pdic/pypdic.cpython-39-x86_64-linux-gnu.so
pdic-0.0.2.dist-info/LICENSE
pdic-0.0.2.dist-info/METADATA
pdic-0.0.2.dist-info/WHEEL
pdic-0.0.2.dist-info/top_level.txt
pdic-0.0.2.dist-info/RECORD
