Metadata-Version: 2.1
Name: pdic
Version: 0.0.2
Summary: Python api (IDL) Transpiler Source-to-source compiler C/C++ to YAML Description based on clang
Home-page: UNKNOWN
Author: Barre Kevin
Author-email: kevin.barre@epitech.eu
License: EUPL
Project-URL: Source, https://github.com/neudinger/pdic
Platform: UNKNOWN
Classifier: Development Status :: 5 - Production/Stable
Classifier: Intended Audience :: Developers
Classifier: Programming Language :: C++
Classifier: Topic :: Software Development
Classifier: Topic :: Scientific/Engineering
Classifier: Typing :: Typed
Classifier: Operating System :: POSIX
Classifier: Operating System :: Unix
Classifier: Operating System :: MacOS
Classifier: Programming Language :: Python :: 3
Classifier: Operating System :: OS Independent
Classifier: Programming Language :: Python :: 3
Classifier: Programming Language :: Python :: 3.6
Classifier: Programming Language :: Python :: 3.7
Classifier: Programming Language :: Python :: 3.8
Classifier: Programming Language :: Python :: 3.9
Classifier: Programming Language :: Python :: 3 :: Only
Requires-Python: >=3.6
Requires-Dist: pyyaml
